{
  "info": {
    "name": "Task Manager API",
    "_postman_id": "12345678-abcd-efgh-ijkl-1234567890ab",
    "description": "Collection Postman pour Task Manager API avec JWT, rôles et endpoints CRUD complets.",
    "schema": "https://schema.getpostman.com/json/collection/v2.1.0/collection.json"
  },
  "item": [
    {
      "name": "Auth",
      "item": [
        {
          "name": "Register",
          "request": {
            "method": "POST",
            "header": [
              {
                "key": "Content-Type",
                "value": "application/json"
              }
            ],
            "url": {
              "raw": "{{baseUrl}}/auth/register",
              "host": ["{{baseUrl}}"],
              "path": ["auth","register"]
            },
            "body": {
              "mode": "raw",
              "raw": "{\n  \"email\": \"test@mail.com\",\n  \"password\": \"123456\"\n}"
            }
          }
        },
        {
          "name": "Login",
          "request": {
            "method": "POST",
            "header": [
              {
                "key": "Content-Type",
                "value": "application/json"
              }
            ],
            "url": {
              "raw": "{{baseUrl}}/auth/login",
              "host": ["{{baseUrl}}"],
              "path": ["auth","login"]
            },
            "body": {
              "mode": "raw",
              "raw": "{\n  \"email\": \"test@mail.com\",\n  \"password\": \"123456\"\n}"
            }
          }
        }
      ]
    },
    {
      "name": "Users",
      "item": [
        {
          "name": "Get All Users",
          "request": {
            "method": "GET",
            "header": [
              {
                "key": "Authorization",
                "value": "Bearer {{token}}"
              }
            ],
            "url": {
              "raw": "{{baseUrl}}/users",
              "host": ["{{baseUrl}}"],
              "path": ["users"]
            }
          }
        },
        {
          "name": "Get User By ID",
          "request": {
            "method": "GET",
            "header": [
              {
                "key": "Authorization",
                "value": "Bearer {{token}}"
              }
            ],
            "url": {
              "raw": "{{baseUrl}}/users/:id",
              "host": ["{{baseUrl}}"],
              "path": ["users",":id"]
            }
          }
        },
        {
          "name": "Delete User",
          "request": {
            "method": "DELETE",
            "header": [
              {
                "key": "Authorization",
                "value": "Bearer {{token}}"
              }
            ],
            "url": {
              "raw": "{{baseUrl}}/users/:id",
              "host": ["{{baseUrl}}"],
              "path": ["users",":id"]
            }
          }
        }
      ]
    },
    {
      "name": "Projects",
      "item": [
        {
          "name": "Create Project",
          "request": {
            "method": "POST",
            "header": [
              { "key": "Authorization", "value": "Bearer {{token}}" },
              { "key": "Content-Type", "value": "application/json" }
            ],
            "url": { "raw": "{{baseUrl}}/projects", "host": ["{{baseUrl}}"], "path": ["projects"] },
            "body": { "mode": "raw", "raw": "{ \"title\": \"Projet A\", \"description\": \"Description\" }" }
          }
        },
        {
          "name": "Get All Projects",
          "request": {
            "method": "GET",
            "header": [{ "key": "Authorization", "value": "Bearer {{token}}" }],
            "url": { "raw": "{{baseUrl}}/projects", "host": ["{{baseUrl}}"], "path": ["projects"] }
          }
        },
        {
          "name": "Get Project By ID",
          "request": {
            "method": "GET",
            "header": [{ "key": "Authorization", "value": "Bearer {{token}}" }],
            "url": { "raw": "{{baseUrl}}/projects/:id", "host": ["{{baseUrl}}"], "path": ["projects",":id"] }
          }
        },
        {
          "name": "Update Project",
          "request": {
            "method": "PUT",
            "header": [
              { "key": "Authorization", "value": "Bearer {{token}}" },
              { "key": "Content-Type", "value": "application/json" }
            ],
            "url": { "raw": "{{baseUrl}}/projects/:id", "host": ["{{baseUrl}}"], "path": ["projects",":id"] },
            "body": { "mode": "raw", "raw": "{ \"title\": \"Updated Title\" }" }
          }
        },
        {
          "name": "Delete Project",
          "request": {
            "method": "DELETE",
            "header": [{ "key": "Authorization", "value": "Bearer {{token}}" }],
            "url": { "raw": "{{baseUrl}}/projects/:id", "host": ["{{baseUrl}}"], "path": ["projects",":id"] }
          }
        },
        {
          "name": "Get Projects By User",
          "request": {
            "method": "GET",
            "header": [{ "key": "Authorization", "value": "Bearer {{token}}" }],
            "url": { "raw": "{{baseUrl}}/projects/user/:userId", "host": ["{{baseUrl}}"], "path": ["projects","user",":userId"] }
          }
        }
      ]
    },
    {
      "name": "Tasks",
      "item": [
        {
          "name": "Create Task",
          "request": {
            "method": "POST",
            "header": [
              { "key": "Authorization", "value": "Bearer {{token}}" },
              { "key": "Content-Type", "value": "application/json" }
            ],
            "url": { "raw": "{{baseUrl}}/tasks", "host": ["{{baseUrl}}"], "path": ["tasks"] },
            "body": { "mode": "raw", "raw": "{ \"title\": \"Task 1\", \"status\": \"TODO\", \"priority\": \"HIGH\", \"projectId\": 1 }" }
          }
        },
        {
          "name": "Get All Tasks",
          "request": {
            "method": "GET",
            "header": [{ "key": "Authorization", "value": "Bearer {{token}}" }],
            "url": { "raw": "{{baseUrl}}/tasks", "host": ["{{baseUrl}}"], "path": ["tasks"] }
          }
        },
        {
          "name": "Get Task By ID",
          "request": {
            "method": "GET",
            "header": [{ "key": "Authorization", "value": "Bearer {{token}}" }],
            "url": { "raw": "{{baseUrl}}/tasks/:id", "host": ["{{baseUrl}}"], "path": ["tasks",":id"] }
          }
        },
        {
          "name": "Update Task",
          "request": {
            "method": "PUT",
            "header": [
              { "key": "Authorization", "value": "Bearer {{token}}" },
              { "key": "Content-Type", "value": "application/json" }
            ],
            "url": { "raw": "{{baseUrl}}/tasks/:id", "host": ["{{baseUrl}}"], "path": ["tasks",":id"] },
            "body": { "mode": "raw", "raw": "{ \"status\": \"DONE\" }" }
          }
        },
        {
          "name": "Delete Task",
          "request": {
            "method": "DELETE",
            "header": [{ "key": "Authorization", "value": "Bearer {{token}}" }],
            "url": { "raw": "{{baseUrl}}/tasks/:id", "host": ["{{baseUrl}}"], "path": ["tasks",":id"] }
          }
        },
        {
          "name": "Get Tasks By Project",
          "request": {
            "method": "GET",
            "header": [{ "key": "Authorization", "value": "Bearer {{token}}" }],
            "url": { "raw": "{{baseUrl}}/tasks/project/:projectId", "host": ["{{baseUrl}}"], "path": ["tasks","project",":projectId"] }
          }
        },
        {
          "name": "Get Tasks With Filters",
          "request": {
            "method": "GET",
            "header": [{ "key": "Authorization", "value": "Bearer {{token}}" }],
            "url": { "raw": "{{baseUrl}}/tasks?status=TODO&priority=HIGH&projectId=1", "host": ["{{baseUrl}}"], "path": ["tasks"], "query":[{"key":"status","value":"TODO"},{"key":"priority","value":"HIGH"},{"key":"projectId","value":"1"}] }
          }
        },
        {
          "name": "Get Prioritized Tasks",
          "request": {
            "method": "GET",
            "header": [{ "key": "Authorization", "value": "Bearer {{token}}" }],
            "url": { "raw": "{{baseUrl}}/tasks/prioritized?userId=1", "host": ["{{baseUrl}}"], "path": ["tasks","prioritized"], "query":[{"key":"userId","value":"1"}] }
          }
        }
      ]
    },
    {
      "name": "Tags",
      "item": [
        {
          "name": "Create Tag",
          "request": {
            "method": "POST",
            "header": [
              { "key": "Authorization", "value": "Bearer {{token}}" },
              { "key": "Content-Type", "value": "application/json" }
            ],
            "url": { "raw": "{{baseUrl}}/tags", "host": ["{{baseUrl}}"], "path": ["tags"] },
            "body": { "mode": "raw", "raw": "{ \"name\": \"Urgent\" }" }
          }
        },
        {
          "name": "Get All Tags",
          "request": {
            "method": "GET",
            "header": [{ "key": "Authorization", "value": "Bearer {{token}}" }],
            "url": { "raw": "{{baseUrl}}/tags", "host": ["{{baseUrl}}"], "path": ["tags"] }
          }
        },
        {
          "name": "Get Tag By ID",
          "request": {
            "method": "GET",
            "header": [{ "key": "Authorization", "value": "Bearer {{token}}" }],
            "url": { "raw": "{{baseUrl}}/tags/:id", "host": ["{{baseUrl}}"], "path": ["tags",":id"] }
          }
        },
        {
          "name": "Delete Tag",
          "request": {
            "method": "DELETE",
            "header": [{ "key": "Authorization", "value": "Bearer {{token}}" }],
            "url": { "raw": "{{baseUrl}}/tags/:id", "host": ["{{baseUrl}}"], "path": ["tags",":id"] }
          }
        }
      ]
    },
    {
      "name": "TaskTags",
      "item": [
        {
          "name": "Add Tag to Task",
          "request": {
            "method": "POST",
            "header": [
              { "key": "Authorization", "value": "Bearer {{token}}" },
              { "key": "Content-Type", "value": "application/json" }
            ],
            "url": { "raw": "{{baseUrl}}/task-tags", "host": ["{{baseUrl}}"], "path": ["task-tags"] },
            "body": { "mode": "raw", "raw": "{ \"taskId\": 1, \"tagId\": 2 }" }
          }
        },
        {
          "name": "Remove Tag from Task",
          "request": {
            "method": "DELETE",
            "header": [{ "key": "Authorization", "value": "Bearer {{token}}" }],
            "url": { "raw": "{{baseUrl}}/task-tags/:id", "host": ["{{baseUrl}}"], "path": ["task-tags",":id"] }
          }
        },
        {
          "name": "Get Tasks By Tag",
          "request": {
            "method": "GET",
            "header": [{ "key": "Authorization", "value": "Bearer {{token}}" }],
            "url": { "raw": "{{baseUrl}}/tasks/tag/:tagId", "host": ["{{baseUrl}}"], "path": ["tasks","tag",":tagId"] }
          }
        }
      ]
    },
    {
      "name": "Dashboard",
      "item": [
        {
          "name": "Get Dashboard",
          "request": {
            "method": "GET",
            "header": [{ "key": "Authorization", "value": "Bearer {{token}}" }],
            "url": { "raw": "{{baseUrl}}/dashboard", "host": ["{{baseUrl}}"], "path": ["dashboard"] }
          }
        },
        {
          "name": "Get Dashboard By Period",
          "request": {
            "method": "GET",
            "header": [{ "key": "Authorization", "value": "Bearer {{token}}" }],
            "url": { "raw": "{{baseUrl}}/dashboard?start=2026-01-01&end=2026-03-30", "host": ["{{baseUrl}}"], "path": ["dashboard"], "query":[{"key":"start","value":"2026-01-01"},{"key":"end","value":"2026-03-30"}] }
          }
        }
      ]
    }
  ],
  "variable": [
    { "key": "baseUrl", "value": "http://localhost:8451/api" },
    { "key": "token", "value": "" }
  ]
}